MANIFEST.in
setup.py
ate_control_app/LICENSE.txt
ate_control_app/README.md
ate_control_app/__init__.py
ate_control_app/control_application.py
ate_control_app/control_connection_handler.py
ate_control_app/launch_control.py
requirements/run.txt
semi_ate_control_app.egg-info/PKG-INFO
semi_ate_control_app.egg-info/SOURCES.txt
semi_ate_control_app.egg-info/dependency_links.txt
semi_ate_control_app.egg-info/entry_points.txt
semi_ate_control_app.egg-info/requires.txt
semi_ate_control_app.egg-info/top_level.txt